internal_logger/__init__.py
internal_logger-2.0.0.dist-info/METADATA
internal_logger-2.0.0.dist-info/WHEEL
internal_logger-2.0.0.dist-info/top_level.txt
internal_logger-2.0.0.dist-info/RECORD
