Metadata-Version: 2.4
Name: internal-logger
Version: 2.0.0
Summary: Fake internal logger for dependency confusion demo
Home-page: https://example.com
Author: SecurityDemo
Author-email: demo@example.com
Dynamic: author
Dynamic: author-email
Dynamic: home-page
Dynamic: summary
